scroll/__init__.py
scroll/generators.py
scroll/helpers.py
scroll/runner.py
scroll/tracer.py
scroll/templates/index.html
scroll/templates/scroll.css
scroll-2021.7.4.dist-info/entry_points.txt
scroll-2021.7.4.dist-info/WHEEL
scroll-2021.7.4.dist-info/METADATA
scroll-2021.7.4.dist-info/RECORD
