Metadata-Version: 2.1
Name: scroll
Version: 2021.7.4
Summary: SCROLL: Automatically generates documentation and unit-tests for python programs
Home-page: https://github.com/SimiCode/scroll
Keywords: scroll documentation unit tests
Author: Edison Abahurire
Author-email: abahedison@gmail.com
Requires-Python: >=3.6
Classifier: Intended Audience :: Developers
Classifier: Development Status :: 4 - Beta
Classifier: Programming Language :: Python
Classifier: Programming Language :: Python :: 3.6
Classifier: Programming Language :: Python :: 3.7
Classifier: Programming Language :: Python :: 3.8
Classifier: Programming Language :: Python :: 3.9
Classifier: Topic :: Software Development :: Libraries :: Python Modules
Classifier: Programming Language :: Python :: Implementation :: CPython
Classifier: License :: OSI Approved :: MIT License
Requires-Dist: click
Project-URL: Bug-Tracker, https://github.com/SimiCode/SCROLL/issues
Project-URL: Documentation, https://github.com/SimiCode/SCROLL/blob/master/README.md
Project-URL: Source-Code, https://github.com/SimiCode/SCROLL/
